pycollectionsx/__init__.py
pycollectionsx/core.py
pycollectionsx-0.1.0.dist-info/METADATA
pycollectionsx-0.1.0.dist-info/WHEEL
pycollectionsx-0.1.0.dist-info/top_level.txt
pycollectionsx-0.1.0.dist-info/RECORD
